{
  "life_context": "1472年生浙江余姚,明代思想家军事家教育家心学集大成者。历任刑部主事左佥都御史等职,平定宁王朱宸濠之乱,晚年讲学于绍兴阳明洞创致良知知行合一之学。",
  "real_works": [
    "《传习录》",
    "《大学问》",
    "《王文成公全书》"
  ],
  "real_quotes": [
    "知行合一——《传习录》",
    "致良知——《传习录》",
    "心即理也——《传习录》",
    "破山中贼易破心中贼难——《王阳明全集》",
    "你未看此花时此花与汝心同归于寂——《传习录》"
  ],
  "mapped_dimensions": {
    "火(心)": "印星对应心即理火主光明",
    "木(良知)": "比劫对应良知木主生生",
    "金(知行)": "官杀对应知行金主决断",
    "水(事上炼)": "食伤对应事上炼水主流动"
  },
  "bazi_analysis_method": "阳明观命以心学为宗不拘于五行之象而重其心。命局吉凶不在格局纯杂而在良知之明暗。致吾心之良知于事事物物则事事物物皆得其理。日主为心之本体十神为之发用——心外无命命外无心。格物致知在命局中磨炼。",
  "unique_monologue": "阳明先生曰:观此命局岂问吉凶乎?夫心外无命命外无心。今之论命者皆逐于五行旺衰用神得失,是犹抛却自家无尽藏沿门持钵效贫儿也。此命五行驳杂官杀混杂,在外人观之乃凶险之格。然吾道:破得官杀之贼心中贼亦破矣。日主坐印星本有良知之明但被财星所蔽。若能在事上磨炼——大运所至之处即是致良知之地——则一棒一条痕一掴一掌血,命局自化凶为吉。知行合一命理在焉。"
}